rsbox/__init__.py
rsbox/data.py
rsbox/example.py
rsbox/misc.py
rsbox/ml.py
rsbox-0.0.15.dist-info/METADATA
rsbox-0.0.15.dist-info/WHEEL
rsbox-0.0.15.dist-info/licenses/LICENSE
rsbox-0.0.15.dist-info/RECORD
