Metadata-Version: 2.1
Name: rsbox
Version: 0.0.15
Summary: A toolbox of utility functions I commonly use when programming in Python.
Project-URL: Homepage, https://github.com/rosikand/rsbox
Author-email: Rohan Sikand <rsikand29@gmail.com>
License: Copyright (c) 2018 The Python Packaging Authority
License-File: LICENSE
Classifier: License :: OSI Approved :: MIT License
Classifier: Operating System :: OS Independent
Classifier: Programming Language :: Python :: 3
Requires-Python: >=3.7
